MANIFEST.in
README.rst
setup.py
integra_setup.egg-info/PKG-INFO
integra_setup.egg-info/SOURCES.txt
integra_setup.egg-info/dependency_links.txt
integra_setup.egg-info/requires.txt
integra_setup.egg-info/top_level.txt
integra_setup.egg-info/zip-safe
setup/__init__.py
setup/admin.py
setup/apps.py
setup/models.py
setup/tests.py
setup/urls.py
setup/views.py
setup/migrations/0001_initial.py
setup/migrations/__init__.py