Metadata-Version: 1.0
Name: integra-setup
Version: 0.1
Summary: A django setup app with angularjs and bootstrap
Home-page: UNKNOWN
Author: Partha.Konda
Author-email: parthasaradhi1992@gmail.com
License: UNKNOWN
Keywords: django-setup,integra-setup
Platform: UNKNOWN
